.gitignore
.gitreview
.pylintrc
.readthedocs.yml
AUTHORS.md
Contributing.rst
LICENSE-3RD-PARTY.txt
LICENSE.txt
README.rst
setup.py
tox.ini
utils.py
.github/workflows/publish.yml
.github/workflows/test.yml
binder/postBuild
docs/Makefile
docs/source/api.rst
docs/source/archetypes.rst
docs/source/architecture.rst
docs/source/conf.py
docs/source/configuration.rst
docs/source/contributing.rst
docs/source/index.rst
docs/source/interaction.rst
docs/source/releasesfile.rst
docs/source/specializations.rst
docs/source/tutorials.rst
docs/source/assets/bbnforge
docs/source/assets/nexus-forge-architecture.png
docs/source/releases/release-notes.rst
docs/source/releases/v0.3-release-notes.rst
docs/source/releases/v0.3.3-release-notes.rst
docs/source/releases/v0.4.0-release-notes.rst
docs/source/releases/v0.5.0-release-notes.rst
docs/source/releases/v0.5.1-release-notes.rst
docs/source/releases/v0.5.2-release-notes.rst
docs/source/releases/v0.6.0-release-notes.rst
docs/source/releases/v0.6.1-release-notes.rst
docs/source/releases/v0.6.2-release-notes.rst
docs/source/releases/v0.6.3-release-notes.rst
docs/source/releases/v0.7.0-release-notes.rst
examples/configurations/demo-resolver/entity-to-resource-mapping.hjson
examples/configurations/demo-resolver/term-to-resource-mapping.hjson
examples/configurations/demo-store/demo-config-with-resolvers.yml
examples/configurations/demo-store/file-to-resource-mapping.hjson
examples/configurations/entitylinking-resolver/entitylinking-mapper-encoder.hjson
examples/configurations/entitylinking-resolver/entitylinking-mapper-es.hjson
examples/configurations/entitylinking-resolver/entitylinking-mapper.hjson
examples/configurations/nexus-resolver/agent-to-resource-mapping.hjson
examples/configurations/nexus-resolver/term-to-resource-mapping.hjson
examples/configurations/nexus-store/file-to-resource-mapping.hjson
examples/configurations/nexus-store/publishing-file-to-resource-mapping.hjson
examples/data/associations.tsv
examples/data/my_data.xwz
nexusforge.egg-info/PKG-INFO
nexusforge.egg-info/SOURCES.txt
nexusforge.egg-info/dependency_links.txt
nexusforge.egg-info/requires.txt
nexusforge.egg-info/top_level.txt
