Metadata-Version: 2.1
Name: nexusforge
Version: 0.8.2
Summary: Building and Using Knowledge Graphs made easy.
Home-page: https://github.com/BlueBrain/nexus-forge
Author: Blue Brain Project, EPFL
License: UNKNOWN
Keywords: framework knowledge graph data science
Platform: UNKNOWN
Classifier: Development Status :: 2 - Pre-Alpha
Classifier: Intended Audience :: Information Technology
Classifier: Intended Audience :: Science/Research
Classifier: Topic :: Scientific/Engineering
Classifier: Programming Language :: Python :: 3 :: Only
Classifier: Natural Language :: English
Classifier: License :: OSI Approved :: GNU Lesser General Public License v3 (LGPLv3)
Requires-Python: >=3.8
Provides-Extra: dev
Provides-Extra: docs
Provides-Extra: linking_sklearn
